static_redirects/__init__.py
static_redirects/apps.py
static_redirects/checks.py
static_redirects/middleware.py
static_redirects/signal_handlers.py
static_redirects/utils.py
django_static_redirects-1.0.0.dist-info/LICENSE
django_static_redirects-1.0.0.dist-info/WHEEL
django_static_redirects-1.0.0.dist-info/METADATA
django_static_redirects-1.0.0.dist-info/RECORD
