Metadata-Version: 2.1
Name: django-static-redirects
Version: 1.0.0
Summary: Static redirects for Django
Author: Jake Howard
Requires-Python: >=3.8
Classifier: License :: OSI Approved
Classifier: License :: OSI Approved :: MIT License
Classifier: Framework :: Django
Classifier: Framework :: Django :: 3.2
Classifier: Framework :: Django :: 4.2
Classifier: Framework :: Django :: 5.0
Classifier: Development Status :: 5 - Production/Stable
Classifier: Programming Language :: Python :: 3
Classifier: Programming Language :: Python :: 3.8
Classifier: Programming Language :: Python :: 3.9
Classifier: Programming Language :: Python :: 3.10
Classifier: Programming Language :: Python :: 3.11
Classifier: Programming Language :: Python :: 3.12
Classifier: Operating System :: OS Independent
Classifier: Topic :: Internet :: WWW/HTTP
Classifier: Topic :: Software Development
Requires-Dist: Django>=3.2
Requires-Dist: ruff ; extra == "dev"
Requires-Dist: black ; extra == "dev"
Project-URL: Changelog, https://github.com/torchbox/django-static-redirects/releases
Project-URL: Issues, https://github.com/torchbox/django-static-redirects/issues
Project-URL: Source, https://github.com/torchbox/django-static-redirects
Provides-Extra: dev
